neomodel/__init__.py
neomodel/cardinality.py
neomodel/config.py
neomodel/core.py
neomodel/exception.py
neomodel/exceptions.py
neomodel/hooks.py
neomodel/match.py
neomodel/match_q.py
neomodel/properties.py
neomodel/relationship.py
neomodel/relationship_manager.py
neomodel/util.py
neomodel/contrib/__init__.py
neomodel/contrib/semi_structured.py
neomodel_next-3.4.5.data/scripts/neomodel_install_labels
neomodel_next-3.4.5.data/scripts/neomodel_remove_labels
test/__init__.py
test/conftest.py
test/test_alias.py
test/test_auto_update.py
test/test_batch.py
test/test_cardinality.py
test/test_cypher.py
test/test_exceptions.py
test/test_hooks.py
test/test_indexing.py
test/test_issue112.py
test/test_issue283.py
test/test_label_drop.py
test/test_label_install.py
test/test_match_api.py
test/test_models.py
test/test_multiprocessing.py
test/test_properties.py
test/test_relationship_models.py
test/test_relationships.py
test/test_relative_relationships.py
test/test_transactions.py
test/test_contrib/__init__.py
test/test_contrib/test_semi_structured.py
neomodel_next-3.4.5.dist-info/AUTHORS.txt
neomodel_next-3.4.5.dist-info/LICENSE
neomodel_next-3.4.5.dist-info/METADATA
neomodel_next-3.4.5.dist-info/WHEEL
neomodel_next-3.4.5.dist-info/top_level.txt
neomodel_next-3.4.5.dist-info/zip-safe
neomodel_next-3.4.5.dist-info/RECORD
