Metadata-Version: 2.1
Name: neomodel-next
Version: 3.4.5
Summary: An object mapper for the neo4j graph database.
Home-page: http://github.com/MardanovTimur/neomodel-next
Author: Robin Edwards; Mardanov Timur
Author-email: timurmardanov97@gmail.com
License: MIT
Keywords: graph neo4j neomodel ORM OGM
Platform: UNKNOWN
Classifier: Development Status :: 5 - Production/Stable
Classifier: Intended Audience :: Developers
Classifier: Operating System :: OS Independent
Classifier: License :: OSI Approved :: MIT License
Classifier: Programming Language :: Python
Classifier: Topic :: Software Development :: Libraries :: Python Modules
Classifier: Programming Language :: Python :: 3.6
Classifier: Topic :: Database
Requires-Dist: neo4j-driver (<1.7.0,>=1.5.2)
Requires-Dist: pytz (>=2016.10)
Requires-Dist: python-dateutil (==2.8.0)
Requires-Dist: numpy (>=1.12.1)
